yapscda/__init__.py
yapscda/test.py
yspscda-0.0.2.dist-info/LICENSE.md
yspscda-0.0.2.dist-info/METADATA
yspscda-0.0.2.dist-info/WHEEL
yspscda-0.0.2.dist-info/top_level.txt
yspscda-0.0.2.dist-info/RECORD
