Metadata-Version: 2.1
Name: yspscda
Version: 0.0.2
Summary: Yet Another Package for Single-Cell Data Analysis
Home-page: https://github.com/spriyansh/yspscda
Author: Priyansh Srivastava
Author-email: spriyansh29@gmail.com
Classifier: Programming Language :: Python :: 3
Classifier: License :: OSI Approved :: MIT License
Classifier: Operating System :: OS Independent
Requires-Python: >=3.6
License-File: LICENSE.md
